{
  "tipo": "SORTEO",
  "id": "sorteo_001",
  "copias": "1",
  "orden": "1",
  "printerName": "Impresora_Termica_Principal",
  "fecha": "2025-06-18",
  "hora": "14:30:00",
  "evento": "Gran Sorteo de Aniversario 2025",
  "nombres": "María Elena",
  "apellidos": "González Rodríguez",
  "cedula": "1234567890",
  "telefono": "0987654321",
  "numeroSorteo": "00587",
  "mensaje": "¡Felicitaciones! Has sido seleccionado en nuestro sorteo especial. Presenta este comprobante en recepción para reclamar tu premio.",
  "pie": "Válido hasta el 30 de junio de 2025 | www.empresa.com | Tel: (02) 123-4567"
}
